aki1_api-0.1.0.dist-info/licenses/LICENSE
myaki_api/__init__.py
myaki_api/main.py
aki1_api-0.1.0.dist-info/METADATA
aki1_api-0.1.0.dist-info/WHEEL
aki1_api-0.1.0.dist-info/top_level.txt
aki1_api-0.1.0.dist-info/RECORD
