Metadata-Version: 2.4
Name: aki1-api
Version: 0.1.0
Summary: A Python API for interacting with Akinator's guessing game
Author-email: Fethi Amari <yasashi91@gmail.com>
License: 
Project-URL: Homepage, https://github.com/yasashi91/aki1-api
Project-URL: Repository, https://github.com/yasashi91/aki1-api
Classifier: Programming Language :: Python :: 3
Classifier: Programming Language :: Python :: 3.8
Classifier: Programming Language :: Python :: 3.9
Classifier: Programming Language :: Python :: 3.10
Classifier: Programming Language :: Python :: 3.11
Classifier: License :: OSI Approved :: MIT License
Classifier: Operating System :: OS Independent
Requires-Python: >=3.8
License-File: LICENSE
Requires-Dist: cloudscraper>=1.2.71
Requires-Dist: beautifulsoup4>=4.12.3
Dynamic: license-file
